aruco.py
aruco_detector.py
easy_arucos-0.0.2.dist-info/METADATA
easy_arucos-0.0.2.dist-info/WHEEL
easy_arucos-0.0.2.dist-info/licenses/LICENSE
easy_arucos-0.0.2.dist-info/RECORD
