Metadata-Version: 2.1
Name: easy_arucos
Version: 0.0.2
Summary: Easy Arucos
Project-URL: Homepage, https://github.com/David-Egea/easy-arucos
Project-URL: Bug Tracker, https://github.com/David-Egea/easy-arucos/issues
Author: davidegea
License: MIT License
License-File: LICENSE
Classifier: License :: OSI Approved :: MIT License
Classifier: Operating System :: OS Independent
Classifier: Programming Language :: Python :: 3.9
Requires-Python: >=3.9
